ibbi/__init__.py
ibbi/data/__init__.py
ibbi/data/ibbi_model_summary.csv
ibbi/data/ibbi_species_distance_matrix.csv
ibbi/data/ibbi_species_table.csv
ibbi/data/model_cards/grounding_dino_detect_model.md
ibbi/data/model_cards/rtdetrx_bb_detect_model.md
ibbi/data/model_cards/yolov10x_bb_detect_model.md
ibbi/data/model_cards/yolov10x_bb_multi_class_detect_model.md
ibbi/data/model_cards/yolov11x_bb_detect_model.md
ibbi/data/model_cards/yolov11x_bb_multi_class_detect_model.md
ibbi/data/model_cards/yolov12x_bb_multi_class_detect_model.md
ibbi/data/model_cards/yolov8x_bb_detect_model.md
ibbi/data/model_cards/yolov8x_bb_multi_class_detect_model.md
ibbi/data/model_cards/yolov9e_bb_detect_model.md
ibbi/data/model_cards/yolov9e_bb_multi_class_detect_model.md
ibbi/data/model_cards/yoloworldv2_bb_detect_model.md
ibbi/evaluate/__init__.py
ibbi/evaluate/embeddings.py
ibbi/evaluate/object_classification.py
ibbi/explain/__init__.py
ibbi/explain/lime.py
ibbi/explain/shap.py
ibbi/models/__init__.py
ibbi/models/_registry.py
ibbi/models/feature_extractors.py
ibbi/models/multi_class.py
ibbi/models/single_class.py
ibbi/models/zero_shot.py
ibbi/utils/__init__.py
ibbi/utils/cache.py
ibbi/utils/data.py
ibbi/utils/hub.py
ibbi/utils/info.py
ibbi-0.2.2.dist-info/METADATA
ibbi-0.2.2.dist-info/WHEEL
ibbi-0.2.2.dist-info/licenses/LICENSE.md
ibbi-0.2.2.dist-info/RECORD
