Metadata-Version: 2.4
Name: ibbi
Version: 0.2.2
Summary: A package for bark and ambrosia beetle identification.
License: MIT
License-File: LICENSE.md
Author: G. Christopher Marais
Requires-Python: >=3.11,<4.0
Classifier: License :: OSI Approved :: MIT License
Classifier: Programming Language :: Python :: 3
Classifier: Programming Language :: Python :: 3.11
Classifier: Programming Language :: Python :: 3.12
Classifier: Programming Language :: Python :: 3.13
Classifier: Programming Language :: Python :: 3.14
Requires-Dist: datasets (>=3.6.0,<4.0.0)
Requires-Dist: hf-xet (>=1.1.3,<2.0.0)
Requires-Dist: huggingface-hub (>=0.34.4,<0.35.0)
Requires-Dist: ipywidgets (>=8.1.7,<9.0.0)
Requires-Dist: lime (>=0.2.0.1,<0.3.0.0)
Requires-Dist: numpy (>=2.2.6,<3.0.0)
Requires-Dist: pandas (>=2.3.0,<3.0.0)
Requires-Dist: pillow (>=11.2.1,<12.0.0)
Requires-Dist: scikit-bio (>=0.7.0,<0.8.0)
Requires-Dist: shap (>=0.48.0,<0.49.0)
Requires-Dist: slicer (>=0.0.8,<0.0.9)
Requires-Dist: tabulate (>=0.9.0,<0.10.0)
Requires-Dist: timm (>=1.0.19,<2.0.0)
Requires-Dist: torch (>=2.1)
Requires-Dist: torchvision (>=0.16.0)
Requires-Dist: transformers (>=4.56.0,<5.0.0)
Requires-Dist: ultralytics (==8.3.139)
Requires-Dist: umap-learn (>=0.5.9.post2,<0.6.0)
Project-URL: Documentation, https://gcmarais.com/IBBI/
Project-URL: Repository, https://github.com/ChristopherMarais/IBBI
